SyncPulse/SyncPulse.py
SyncPulse/__init__.py
SyncPulse/__main__.py
SyncPulse-2.9.0.dist-info/METADATA
SyncPulse-2.9.0.dist-info/WHEEL
SyncPulse-2.9.0.dist-info/entry_points.txt
SyncPulse-2.9.0.dist-info/top_level.txt
SyncPulse-2.9.0.dist-info/RECORD
